mailgun_cli/__init__.py
mailgun_cli/cli.py
mailgun_cli/forward.py
mailgun_cli/mailgun.py
mailgun_cli-0.1.9.dist-info/entry_points.txt
mailgun_cli-0.1.9.dist-info/LICENSE
mailgun_cli-0.1.9.dist-info/WHEEL
mailgun_cli-0.1.9.dist-info/METADATA
mailgun_cli-0.1.9.dist-info/RECORD
